{
  "bozza": 1,
  "ucraina–russia": 1,
  "morto": 3,
  "bomba": 1,
  "rottura": 1,
  "alcaraz": 1,
  "ferrero": 1,
  "sinner": 1,
  "natale": 5,
  "meloni": 2,
  "social": 2,
  "militare": 1,
  "augurio": 5,
  "presepe": 1,
  "governo": 1,
  "rivoluzione": 1,
  "indagato": 1,
  "scontro": 1,
  "sindaco": 1,
  "bufera": 1,
  "scuola": 1,
  "politico": 1,
  "testa": 1,
  "recupera": 1,
  "zelensky": 7,
  "zona": 1,
  "piano": 4,
  "pace": 3,
  "russo": 3,
  "speciale": 1,
  "ritiro": 1,
  "sorella": 1,
  "burocratico": 1,
  "yacht": 1,
  "problema": 1,
  "emilia-romagna": 1,
  "massimo": 1,
  "allerto": 1,
  "torrente": 1,
  "rosso": 1,
  "cristiano": 1,
  "barca": 1,
  "lontano": 1,
  "aereo": 2,
  "ronaldo": 1,
  "corazzata": 1,
  "esperto": 1,
  "flotta": 1,
  "presidente": 1,
  "trump": 3,
  "supernave": 1,
  "durov": 1,
  "figlio": 4,
  "soldi": 1,
  "madre": 1,
  "terra": 1,
  "centinaio": 2,
  "seggiovia": 1,
  "calciatore": 1,
  "catherine": 1,
  "mamma": 1,
  "alba": 1,
  "vaccino": 1,
  "bosco": 3,
  "sveglia": 1,
  "diktat": 1,
  "famiglia": 3,
  "putin": 3,
  "renne": 1,
  "strage": 1,
  "guerra": 5,
  "lupi": 1,
  "reportage": 1,
  "altro": 1,
  "donna": 1,
  "epstein": 2,
  "volta": 1,
  "carta": 1,
  "previsione": 1,
  "shutdown": 1,
  "ombra": 1,
  "tassa": 2,
  "pacco": 1,
  "novità": 1,
  "pensione": 1,
  "banca": 1,
  "estraneo": 1,
  "legge": 1,
  "stop": 1,
  "ultimo": 2,
  "emendamento": 1,
  "piatto": 1,
  "cultura": 1,
  "encefalogramma": 1,
  "cardini": 1,
  "destra": 1,
  "ragione": 1,
  "bambino": 1,
  "diritto": 1,
  "gennaio": 1,
  "gatti": 1,
  "scambio": 1,
  "mese": 1,
  "ricci": 1,
  "chiesa": 1,
  "natività": 1,
  "indagine": 1,
  "delegazione": 1,
  "incidente": 1,
  "mandare": 1,
  "luogo": 1,
  "nazista": 1,
  "pronto": 1,
  "simbolo": 1,
  "vaso": 1,
  "estorsione": 1,
  "petrolio": 1,
  "venti": 1,
  "sequestro": 1,
  "conferma": 1,
  "rottame": 1,
  "ministro": 1,
  "yerlikaya": 1,
  "mohammed": 1,
  "ali": 1,
  "capo": 1,
  "ahmed": 1,
  "al-haddad": 2,
  "esercito": 1,
  "europeo": 2,
  "breton": 2,
  "piattaforma": 1,
  "generale": 1,
  "nero": 1,
  "polizia": 1,
  "agente": 3,
  "chilometro": 1,
  "coda": 1,
  "leone": 1,
  "xiv": 1,
  "notte": 1,
  "papa": 1,
  "giubileo": 1,
  "messa": 1,
  "celebrazione": 1,
  "chiusura": 1,
  "governatore": 1,
  "latitante": 2,
  "pericoloso": 2,
  "milione": 1,
  "contrattuale": 1,
  "dipendente": 1,
  "aumento": 1,
  "orgoglioso": 2,
  "base": 1,
  "risposta": 1,
  "dato": 1,
  "antitrust": 1,
  "clausola": 1,
  "sospenda": 1,
  "truffa": 1,
  "sms": 1,
  "persona": 1,
  "strada": 1,
  "pirata": 1,
  "tech": 1,
  "visto": 3,
  "lista": 1,
  "radice": 1,
  "inaugura": 1,
  "hotel": 1,
  "jong-un": 1,
  "immagine": 1,
  "resort": 1,
  "ispezione": 1,
  "montagna": 1,
  "dossier": 1,
  "punto": 2,
  "rinuncia": 1,
  "chiarimente": 1,
  "commissario": 1,
  "commissione": 1,
  "veto": 1,
  "ozaki": 1,
  "addio": 1,
  "jumbo": 1,
  "golf": 1,
  "libero": 1,
  "dollaro": 1,
  "maltempo": 1,
  "evacuazione": 1,
  "esplosione": 2,
  "attentatore": 1,
  "vittima": 1,
  "whatsapp": 1,
  "salvini": 1,
  "violenza": 1,
  "senso": 1,
  "politica": 1,
  "depressione": 1,
  "identità": 1,
  "premier": 1,
  "rientrare": 1,
  "caso": 1,
  "alert": 1,
  "mers": 1,
  "viaggiatore": 1,
  "oms": 1,
  "dettaglio": 1,
  "magnitudo": 1,
  "terremoto": 1,
  "denunciare": 1,
  "ure ne": 1,
  "domenica": 1,
  "spot": 1,
  "televisione": 1,
  "pronti": 1,
  "funzionario": 1,
  "poliziotto": 1,
  "ucraina-russia": 1,
  "gonfiato": 1,
  "battaglia": 1,
  "nato": 2,
  "mosca": 8,
  "kiev": 2,
  "miami": 2,
  "usa": 10,
  "manovra": 2,
  "europa": 2,
  "libia": 2,
  "ucraina": 4,
  "russia": 3
}