{
  "mattarella": 4,
  "commercio": 1,
  "chiudere": 1,
  "guerra": 4,
  "paralisi": 1,
  "news": 1,
  "vero": 1,
  "vannacci": 1,
  "replica": 1,
  "meloni": 12,
  "estero": 2,
  "ministero": 1,
  "famiglia": 3,
  "ricerca": 1,
  "sorella": 1,
  "governo": 2,
  "sbagliato": 1,
  "medico": 2,
  "auto": 1,
  "chilo": 1,
  "pesce": 1,
  "formaggio": 1,
  "tavola": 1,
  "mondiale": 2,
  "minaccia": 1,
  "lite": 1,
  "von": 1,
  "leyen": 1,
  "banco": 1,
  "caos": 1,
  "aula": 1,
  "volta": 1,
  "donna": 2,
  "ladro": 2,
  "anno": 3,
  "suv": 1,
  "cerimonia": 1,
  "shakira": 1,
  "inaugurale": 1,
  "primo": 1,
  "bocelli": 1,
  "ritorno": 1,
  "futuro": 1,
  "brexit": 1,
  "società": 1,
  "corruzione": 1,
  "persona": 1,
  "zaire-emery": 1,
  "giovane": 2,
  "bar": 1,
  "hotel": 1,
  "proporzionale": 1,
  "maggioranza": 1,
  "listone": 1,
  "davydov": 1,
  "generale": 1,
  "missile": 2,
  "stop": 2,
  "orario": 1,
  "sindacato": 1,
  "base": 1,
  "giugno": 2,
  "treno": 1,
  "protesta": 4,
  "sciopero": 1,
  "riforma": 1,
  "regione": 1,
  "male": 2,
  "leonardo": 1,
  "tedesco": 2,
  "divieto": 1,
  "coppa": 1,
  "mondo": 1,
  "conflitto": 1,
  "razzisto": 1,
  "disgustoso": 1,
  "città": 2,
  "violenza": 3,
  "trump": 4,
  "massimo": 1,
  "inflazione": 1,
  "ironico": 1,
  "divano": 1,
  "dazn": 1,
  "partita": 2,
  "resto": 1,
  "serio": 1,
  "ridere": 1,
  "comicità": 1,
  "idea": 1,
  "potere": 1,
  "difetto": 1,
  "eterno": 1,
  "economia": 1,
  "vignetta": 1,
  "arena": 1,
  "incontro": 2,
  "petroliera": 1,
  "indiano": 1,
  "attacco": 3,
  "marittimo": 1,
  "lavoro": 1,
  "satellite": 1,
  "timelapse": 1,
  "vista": 3,
  "comunicazione": 3,
  "paura": 1,
  "migrante": 2,
  "volto": 1,
  "drone": 2,
  "gaudí": 1,
  "cielo": 1,
  "festa": 1,
  "strada": 1,
  "immigrato": 2,
  "guerrigliare": 1,
  "pogrom": 1,
  "molotov": 1,
  "arresto": 1,
  "polizia": 2,
  "rottamazione": 1,
  "imu": 1,
  "acciso": 1,
  "multa": 1,
  "tassa": 1,
  "iva": 1,
  "papa": 3,
  "umano": 2,
  "molo": 1,
  "via": 1,
  "domanda": 1,
  "finanziamento": 1,
  "borgo": 1,
  "progetto": 1,
  "rete": 1,
  "affresco": 1,
  "revisore": 2,
  "presidente": 2,
  "miele": 2,
  "protagonista": 1,
  "privatizzazione": 1,
  "addio": 1,
  "spicco": 1,
  "diritto": 2,
  "stagione": 1,
  "lato": 1,
  "tecnologia": 1,
  "domiciliare": 1,
  "tossicodipendente": 1,
  "alcoldipendente": 1,
  "are": 1,
  "critico": 1,
  "franco": 1,
  "negoziato": 3,
  "autorevole": 3,
  "reazione": 1,
  "autostrada": 1,
  "capacità": 1,
  "f-35b": 1,
  "atterraggio": 1,
  "ministro": 1,
  "risorsa": 1,
  "armato": 1,
  "forza": 1,
  "politico": 1,
  "commerciale": 1,
  "tesla": 1,
  "guida": 1,
  "autonomo": 1,
  "assistita": 1,
  "sistema": 1,
  "inferno": 1,
  "accordo": 2,
  "notizia": 1,
  "ultimo": 2,
  "bombardamento": 1,
  "lavorazione": 1,
  "greggio": 1,
  "sociale": 1,
  "immigrazione": 1,
  "tensione": 1,
  "conto": 2,
  "disordine": 1,
  "risultato": 1,
  "pubblicazione": 1,
  "indagine": 1,
  "pace": 2,
  "multilateralismo": 1,
  "luiss": 1,
  "focus": 1,
  "diplosec2026": 1,
  "fuga": 1,
  "dramma": 1,
  "povertà": 1,
  "dipinto": 1,
  "leopardi": 1,
  "antiche": 1,
  "meloni:\"burocrati": 1,
  "canarie": 1,
  "sanzione": 1,
  "colono": 1,
  "ben-gvir": 1,
  "figura": 1,
  "fuoco": 1,
  "padre": 1,
  "oscar": 1,
  "ridley": 1,
  "scott": 1,
  "ondata": 1,
  "lega": 1,
  "salvini": 1,
  "squadra": 1,
  "appello": 1,
  "fiamma": 1,
  "edifici": 1,
  "autorevol": 1,
  "inviato": 1,
  "aiuto": 1,
  "pressione": 3,
  "battuto": 1,
  "segreto": 1,
  "lettera": 1,
  "pop": 1,
  "privato": 1,
  "confessione": 1,
  "fantasma": 1,
  "giorno": 1,
  "altro": 1,
  "presidenziale": 1,
  "voto": 1,
  "luglio": 1,
  "esplosion": 1,
  "obiettivo": 1,
  "molteplice": 1,
  "raffica": 1,
  "sindaco": 1,
  "elezione": 1,
  "campo": 1,
  "corsa": 1,
  "editoriale": 1,
  "rossi": 1,
  "successore": 1,
  "decreto": 1,
  "attuativo": 1,
  "difesa": 1,
  "individuo": 2,
  "freno": 1,
  "rincaro": 1,
  "ets": 1,
  "emissione": 1,
  "quota": 1,
  "vaccino": 1,
  "contratto": 1,
  "asilo": 1,
  "italia-albania": 1,
  "avvocata": 1,
  "raffinerio": 1,
  "russo": 1,
  "krasnodar": 1,
  "cannone": 1,
  "acqua": 1,
  "vicino": 1,
  "scontro": 1,
  "diretta": 1,
  "ordine": 1,
  "mosca": 2,
  "senato": 3,
  "ucraina": 6,
  "roma": 2,
  "belfast": 8,
  "usa": 5,
  "consiglio europeo": 2,
  "camera": 4,
  "proteste anti": 2,
  "seconda notte": 3,
  "collegio": 2,
  "conti csm": 2,
  "ponte messina": 2,
  "collegio revisori conti csm": 2,
  "iran": 7,
  "russia": 3,
  "hormuz": 2,
  "kiev": 5,
  "sostegno": 2,
  "ue individui": 2
}