{
  "racism": 1,
  "let": 1,
  "death": 5,
  "soldier": 2,
  "education": 2,
  "nigeria": 2,
  "inquest": 2,
  "boss": 2,
  "failure": 2,
  "poll": 5,
  "election": 3,
  "job": 8,
  "tip": 1,
  "solution": 1,
  "killing": 2,
  "talk": 5,
  "conflict": 2,
  "finalise": 2,
  "gibraltar": 2,
  "red": 1,
  "condemn": 1,
  "fan": 1,
  "potential": 1,
  "personality": 1,
  "overshadow": 1,
  "overperformer": 1,
  "villa": 1,
  "driver": 1,
  "old": 1,
  "medium": 5,
  "push": 2,
  "leader": 2,
  "standard": 2,
  "voter": 3,
  "politic": 4,
  "seeker": 3,
  "hotel": 3,
  "asset": 2,
  "profit": 2,
  "national": 2,
  "mumsnet": 1,
  "warning": 1,
  "under-16": 1,
  "gamble": 1,
  "slump": 1,
  "break": 1,
  "monarchy": 1,
  "podcast": 1,
  "unveil": 1,
  "landmark": 1,
  "principle": 1,
  "industry": 1,
  "unit": 1,
  "error": 1,
  "childbirth": 1,
  "magic": 1,
  "surface": 1,
  "friend": 1,
  "stage": 1,
  "succession": 1,
  "storm": 1,
  "tragedy": 1,
  "exile": 1,
  "vibe": 1,
  "child": 2,
  "pawn": 1,
  "restriction": 1,
  "goal": 1,
  "condescension": 1,
  "shooting": 1,
  "sale": 1,
  "orbán": 1,
  "reach": 2,
  "agreement": 1,
  "axe": 2,
  "trial": 1,
  "patient": 1,
  "praise": 1,
  "tariff": 1,
  "cut": 1,
  "renew": 1,
  "cry": 1,
  "fire": 1,
  "document": 1,
  "airport": 1,
  "arrest": 2,
  "loan": 2,
  "turn": 1,
  "pressure": 1,
  "ramadan": 1,
  "side": 1,
  "money": 1,
  "beach": 1,
  "wine": 1,
  "duty": 1,
  "crisis": 1,
  "wall": 1,
  "dread": 1,
  "500k": 1,
  "falcon": 1,
  "reality": 1,
  "heartbroken": 1,
  "20k": 1,
  "chemotherapy": 1,
  "thief": 1,
  "rival": 1,
  "defender": 1,
  "row": 1,
  "main": 1,
  "family": 1,
  "charity": 1,
  "trust": 1,
  "reader": 1,
  "voice": 1,
  "visit": 1,
  "file": 1,
  "cocktail": 1,
  "suspicion": 1,
  "aide": 1,
  "area": 1,
  "buyer": 1,
  "student": 1,
  "code": 1,
  "exploitation": 1,
  "sex": 1,
  "gateway": 1,
  "investor": 1,
  "result": 1,
  "arm": 1,
  "rule": 1,
  "way": 1,
  "pair": 1,
  "missile": 1,
  "meet": 1,
  "drink": 1,
  "kyiv": 1,
  "accusation": 1,
  "appeal": 1,
  "jail": 3,
  "apologise": 2,
  "advocate": 1,
  "war": 1,
  "firm": 1,
  "night": 1,
  "newspaper": 1,
  "mob": 1,
  "arrival": 1,
  "rise": 1,
  "speaker": 1,
  "temperature": 1,
  "colour": 1,
  "explosion": 1,
  "jersey": 2,
  "dying law": 2,
  "cuba": 4,
  "us registered speedboat": 3,
  "israeli soldiers": 2,
  "palestinian boy": 2,
  "israeli": 2,
  "palestinian": 3,
  "chimamanda ngozi adichie toddler": 2,
  "chimamanda ngozi adichies": 2,
  "royal mail bosses": 2,
  "royal mail": 2,
  "letter delivery failures": 2,
  "parliament": 2,
  "gorton": 6,
  "denton": 5,
  "gen z protest killings": 2,
  "gen z": 2,
  "police order": 2,
  "school uniform": 2,
  "nepal": 2,
  "bbc": 2,
  "iran": 6,
  "post brexit": 2,
  "post brexit border deal": 2,
  "kim jong un": 4,
  "kim jong": 4,
  "north korea": 4,
  "ocado": 5,
  "trump": 6,
  "south": 2,
  "original journalism": 4,
  "ai standards": 2,
  "sky news": 2,
  "media leaders": 2,
  "suitcase murder": 2,
  "american": 2,
  "bali": 3,
  "restructuring plan": 2,
  "gorton denton byelection": 2,
  "polanski and farage": 2,
  "final pitch": 2,
  "media coalition": 2,
  "guardian": 3,
  "unpaid use": 2,
  "asylum seekers": 3,
  "wpp": 2,
  "ai threat": 2,
  "radical shake": 2,
  "rolls royce": 2,
  "rolls royce profits": 2,
  "ai datacentre power": 2,
  "booming demand": 2,
  "cost saving drive": 2,
  "dual nationals": 2,
  "home office": 2,
  "starmer": 3,
  "labour": 4,
  "trump administration": 2,
  "tommy robinson": 2,
  "andrew mountbatten windsor": 3,
  "australia": 2,
  "ukraine": 3,
  "nuclear talks": 2,
  "second suspect": 2,
  "manchester": 2,
  "manchester mosque": 2,
  "kemi badenoch": 2,
  "china": 2,
  "jimmy lais": 2,
  "jimmy lai fraud conviction": 2
}