{
  "crackdown": 2,
  "protester": 3,
  "clash": 2,
  "dozen": 2,
  "thousand": 2,
  "ice": 2,
  "protest": 3,
  "medium": 2,
  "tory": 1,
  "under-16": 2,
  "court": 1,
  "target": 2,
  "country": 1,
  "roadwork": 1,
  "hall": 1,
  "saving": 1,
  "time": 1,
  "record": 1,
  "baby": 1,
  "dad": 1,
  "pothole": 3,
  "rate": 1,
  "island": 1,
  "love": 1,
  "papers": 1,
  "crisis": 1,
  "wildfire": 1,
  "sinner": 2,
  "winner": 2,
  "durian": 2,
  "hermès": 2,
  "founder": 3,
  "price": 2,
  "electricity": 2,
  "family": 4,
  "champion": 1,
  "lynx": 1,
  "force": 2,
  "point": 1,
  "bear": 1,
  "packers": 1,
  "ash": 1,
  "player": 1,
  "god": 2,
  "comeback": 2,
  "ptsd": 2,
  "school": 2,
  "smartphone": 2,
  "cat": 2,
  "migrant": 2,
  "mouse": 2,
  "council": 2,
  "organiser": 2,
  "charity": 1,
  "heart": 1,
  "hope": 1,
  "line": 2,
  "government": 1,
  "violence": 2,
  "brewer": 1,
  "crop": 1,
  "stout": 1,
  "cream": 1,
  "paramilitary": 1,
  "citizen": 2,
  "board": 1,
  "structure": 1,
  "hectare": 1,
  "town": 1,
  "program": 1,
  "request": 1,
  "regime": 2,
  "election": 1,
  "website": 1,
  "driver": 1,
  "fine": 1,
  "alliance": 1,
  "moment": 1,
  "threat": 2,
  "age": 1,
  "rock": 1,
  "payment": 1,
  "household": 1,
  "caravan": 1,
  "warning": 1,
  "tree": 1,
  "edge": 1,
  "investor": 1,
  "bain": 1,
  "fiction": 1,
  "talk": 1,
  "ally": 1,
  "euro": 1,
  "economist": 1,
  "money": 1,
  "defence": 1,
  "salute": 1,
  "battle": 1,
  "answer": 1,
  "minister": 1,
  "five": 1,
  "violent clashes": 2,
  "iran": 3,
  "iran protesters": 3,
  "minneapolis": 2,
  "thousands march": 2,
  "sexual harassment": 2,
  "state": 2,
  "us military": 2,
  "syria": 2,
  "islamic state targets": 2,
  "islamic": 2,
  "canada": 2,
  "golden globes": 2,
  "china": 2,
  "luxury fruit": 2,
  "china billion dollar appetite": 2,
  "bob weir": 4,
  "grateful dead": 4,
  "grateful dead co": 2,
  "american": 2,
  "soaring energy prices": 2,
  "american families": 2,
  "last kurdish": 2,
  "ceasefire deal": 2,
  "aleppo": 2,
  "last kurdish forces": 2,
  "gen z": 2,
  "growing call": 2,
  "daily game": 2,
  "germany": 2,
  "illegal migrants": 2,
  "pride organisers": 2,
  "movement history": 2,
  "financial challenge": 2,
  "jesy nelson": 2,
  "sma": 2,
  "jesy nelson campaign": 2,
  "charlie nunn": 2,
  "banking boss": 2,
  "lloyds ceo charlie nunn": 2,
  "bonus hike": 2,
  "lloyds": 2,
  "nhs": 2,
  "succession creator jesse armstrong": 2,
  "impostor syndrome": 2,
  "jesse armstrong": 2,
  "venezuela": 2,
  "adelaide festival": 2,
  "randa abdel fattah": 2,
  "trumps greenland": 2,
  "trump greenland threats": 2,
  "storm goretti": 3
}