{
  "innocente": 1,
  "vigliaccato": 1,
  "padre": 1,
  "andrea": 1,
  "sempio": 1,
  "ansia": 2,
  "compagno": 1,
  "inciampo": 1,
  "transatlantico": 1,
  "iceberg": 1,
  "agguato": 1,
  "emery": 1,
  "unai": 1,
  "centro": 1,
  "giovedì": 1,
  "impero": 1,
  "uomo": 1,
  "provincia": 1,
  "bunker": 1,
  "prova": 2,
  "cibo": 1,
  "guerra": 3,
  "berlino": 1,
  "patto": 1,
  "sirena": 1,
  "politico": 1,
  "largo": 1,
  "campo": 1,
  "rischio": 2,
  "ritiro": 1,
  "epidemia": 1,
  "ebola": 2,
  "pianta": 1,
  "serra": 1,
  "afrodite": 1,
  "amplesso": 1,
  "inflazione": 1,
  "crescitare": 1,
  "nero": 1,
  "dimezzato": 1,
  "verità": 1,
  "poker": 1,
  "antonelli": 1,
  "vetta": 2,
  "alpinista": 2,
  "scempio": 1,
  "impresa": 1,
  "sorella": 2,
  "boss": 1,
  "altro": 1,
  "avvocata": 1,
  "perquisizione": 1,
  "saddam": 1,
  "segreto": 2,
  "clan": 1,
  "principessa": 1,
  "storia": 1,
  "stesso": 1,
  "adesione": 1,
  "cos’": 1,
  "light": 1,
  "attivisto": 1,
  "energumeno": 1,
  "devastante": 1,
  "immune": 1,
  "maggio": 1,
  "disponibile": 1,
  "concorsire": 1,
  "scadenza": 1,
  "fine": 1,
  "posto": 1,
  "linea": 1,
  "giudice": 1,
  "sicurezza": 1,
  "cappio": 1,
  "polizia": 1,
  "imprigionato": 1,
  "antisemitismo": 1,
  "ossigeno": 1,
  "sabbia": 1,
  "ricostruzione": 1,
  "maldive": 1,
  "dubbi": 1,
  "attrezzatura": 1,
  "bombola": 1,
  "inadatto": 1,
  "corpo": 1,
  "muta": 1,
  "sinistra": 1,
  "città": 1,
  "ribaltone": 1,
  "mappa": 1,
  "tesoro": 1,
  "confine": 1,
  "calcio": 1,
  "mourinho": 1,
  "abbatto": 1,
  "farioli": 1,
  "febbre": 1,
  "figlio": 2,
  "profetico": 1,
  "grande": 1,
  "romanzo": 1,
  "genio": 1,
  "asimov": 1,
  "futuro": 1,
  "fila": 1,
  "centinaio": 1,
  "versante": 1,
  "record": 1,
  "nepalese": 1,
  "eterno": 1,
  "anno": 1,
  "tempio": 1,
  "animale": 1,
  "manette": 1,
  "cuccioli": 1,
  "trafficante": 1,
  "iguana": 1,
  "bagaglio": 1,
  "stop": 1,
  "ballo": 1,
  "senatore": 1,
  "trump": 3,
  "repubblicano": 1,
  "sala": 1,
  "fondo": 2,
  "mattina": 2,
  "attivista": 3,
  "valore": 1,
  "ambasciatore": 1,
  "ben-gvir": 1,
  "truppa": 1,
  "nucleare": 1,
  "social": 1,
  "seguire": 1,
  "influencer": 1,
  "differenza": 1,
  "reddito": 1,
  "diffuso": 1,
  "under": 1,
  "malattia": 1,
  "emergenza": 1,
  "viaggio": 1,
  "turismo": 1,
  "strapotere": 1,
  "center": 1,
  "sabato": 1,
  "call": 1,
  "online": 1,
  "immigrato": 1,
  "giovane": 1,
  "portale": 2,
  "pensione": 1,
  "novità": 1,
  "ministero": 1,
  "tfr": 1,
  "dazio": 1,
  "minipacco": 1,
  "europeo": 2,
  "metà": 1,
  "luglio": 1,
  "traffico": 1,
  "tassa": 1,
  "medio": 1,
  "contratto": 1,
  "aumento": 1,
  "euro": 1,
  "orario": 1,
  "ridotto": 1,
  "piano": 1,
  "comune": 1,
  "musumeci": 1,
  "dogane": 1,
  "accisa": 2,
  "energia": 1,
  "miliardo": 1,
  "poesia": 1,
  "racconto": 1,
  "presente": 1,
  "vittima": 1,
  "ddl": 1,
  "eurocamera": 1,
  "tutele": 1,
  "crescita": 1,
  "vulnerabile": 1,
  "paese": 1,
  "commissione": 1,
  "associato": 2,
  "membro": 2,
  "sanzione": 1,
  "notizia": 1,
  "khamenei": 1,
  "ultimo": 1,
  "uranio": 1,
  "terzo": 1,
  "meloni": 2,
  "frana": 1,
  "giorno": 1,
  "rivelazione": 1,
  "ufficio": 1,
  "caso": 2,
  "delmastro": 1,
  "appello": 1,
  "stima": 1,
  "volo": 1,
  "soldo": 1,
  "sisma": 1,
  "scuola": 1,
  "lungo": 1,
  "intenso": 1,
  "striscia": 1,
  "morire": 1,
  "investa": 1,
  "centrodestra": 1,
  "rimonta": 1,
  "risorsa": 1,
  "governo": 3,
  "interno": 1,
  "caccia": 1,
  "speranza": 1,
  "crisi": 1,
  "libertà": 1,
  "incatenato": 1,
  "spogliati": 1,
  "caverna": 1,
  "cuore": 1,
  "virus": 1,
  "contagiato": 1,
  "reale": 1,
  "invisibile": 1,
  "superiore": 1,
  "volta": 1,
  "strage": 1,
  "mediatore": 1,
  "lettera": 1,
  "lavoro": 1,
  "intento": 1,
  "proposta": 1,
  "hormuz": 1,
  "timore": 1,
  "chiusura": 1,
  "pressione": 1,
  "milano-tel": 1,
  "conte": 1,
  "gemellaggio": 1,
  "utile": 1,
  "mese": 1,
  "operativo": 1,
  "bollywood": 1,
  "vicino": 1,
  "vita": 1,
  "italia-india": 1,
  "asse": 1,
  "dolce": 1,
  "ira": 1,
  "legare": 1,
  "rosso": 1,
  "diritto": 1,
  "mattarella": 1,
  "inginocchiato": 1,
  "violazione": 1,
  "flotilla": 7,
  "protezione civile": 2,
  "everest": 2,
  "ucraina": 2,
  "merz": 2,
  "kiev": 3,
  "israele": 2,
  "previdenza complementare": 2,
  "iran": 2,
  "napoli": 2
}