{
  "sabotaggio": 2,
  "stazione": 1,
  "prigioniero": 1,
  "rassegnato": 1,
  "alto": 1,
  "silenzi": 1,
  "verità": 1,
  "ospedale": 1,
  "trapianto": 1,
  "mese": 2,
  "cuore": 1,
  "attesa": 1,
  "schillaci": 2,
  "responsabilità": 1,
  "sistema": 1,
  "cura": 1,
  "bimbo": 1,
  "famiglia": 1,
  "tumore": 1,
  "disparità": 1,
  "medico": 1,
  "fiducia": 1,
  "pattuglia": 1,
  "campo": 1,
  "treno": 1,
  "piano": 1,
  "binario": 1,
  "antiterrorismo": 1,
  "assalto": 1,
  "paura": 1,
  "pazzo": 1,
  "trump": 3,
  "giochi": 1,
  "bulbarelli": 1,
  "cda": 1,
  "spesa": 1,
  "danno": 1,
  "destra": 1,
  "fine": 2,
  "follini": 1,
  "ragazzo": 1,
  "uomo": 1,
  "folle": 1,
  "papà": 1,
  "stroppa": 1,
  "striscia": 1,
  "meloni": 2,
  "osservatore": 1,
  "merz": 1,
  "fascinazione": 1,
  "premier": 1,
  "patriota": 1,
  "mondo": 1,
  "costituzione": 1,
  "centrosinistra": 1,
  "schlein": 1,
  "rivolta": 1,
  "riaprire": 1,
  "condizione": 1,
  "errore": 1,
  "ministra": 1,
  "lite": 1,
  "paese": 1,
  "alleato": 3,
  "estero": 1,
  "zelensky": 2,
  "tregua": 1,
  "elezione": 1,
  "pronto": 2,
  "culla": 1,
  "peluca": 1,
  "sterile": 1,
  "mamma": 1,
  "orsacchiotto": 1,
  "malinin": 1,
  "ala": 1,
  "isola": 1,
  "battaglia": 1,
  "usa-danimarca": 1,
  "ghiaccio": 1,
  "felice": 1,
  "nota": 1,
  "hockey": 1,
  "chiellini": 1,
  "furioso": 1,
  "rocchi": 1,
  "comolli": 1,
  "rotto": 1,
  "ruggito": 1,
  "antonio": 1,
  "gigante": 2,
  "giusto": 1,
  "favorita": 1,
  "brignone": 2,
  "william": 1,
  "kate": 1,
  "social": 1,
  "politica": 2,
  "michelle": 1,
  "decoro": 1,
  "scimmie": 1,
  "rano": 2,
  "ecuadoriano": 1,
  "navalny": 2,
  "veleno": 2,
  "europeo": 1,
  "discutere ne": 1,
  "ucraina": 1,
  "governance": 2,
  "guerra": 1,
  "gara": 1,
  "prova": 1,
  "goggia": 1,
  "israeliano": 1,
  "palestinese": 2,
  "aereo": 1,
  "occidente": 1,
  "maschio": 1,
  "lezione": 1,
  "studente": 1,
  "clownesco": 1,
  "popolo": 1,
  "mano": 1,
  "accusa": 1,
  "pontiero": 1,
  "ue-usa": 1,
  "nucleare": 1,
  "accordo": 1,
  "compromesso": 1,
  "raid": 1,
  "concessione": 1,
  "putin": 1,
  "board": 2,
  "usa": 4,
  "mosca": 4,
  "onu": 2,
  "kiev": 2
}