{
  "intimo": 1,
  "nozza": 1,
  "amico": 2,
  "reazione": 1,
  "calcio": 1,
  "uccidere": 1,
  "migliaio": 3,
  "protesta": 2,
  "supremo": 1,
  "diretta": 2,
  "maldini": 1,
  "premier": 1,
  "primo": 2,
  "delago": 1,
  "libertà": 1,
  "vittoria": 1,
  "stazione": 1,
  "ragazzo": 3,
  "testa": 1,
  "accetta": 1,
  "rissa": 1,
  "scuola": 3,
  "omicida": 1,
  "fortunato": 1,
  "club": 1,
  "bologna-fiorentina": 1,
  "padre": 3,
  "annuncio": 2,
  "ambra": 1,
  "cacciare": 1,
  "liceale": 1,
  "aggressore": 1,
  "ruolo": 1,
  "dubbio": 1,
  "paratici": 1,
  "ferrari": 1,
  "futuro": 2,
  "ice": 3,
  "trump": 12,
  "ossessione": 1,
  "sondaggio": 1,
  "violenza": 1,
  "presidente": 2,
  "anno": 2,
  "addio": 1,
  "board": 3,
  "presenza": 2,
  "disponibili": 1,
  "meloni": 10,
  "tokyo": 2,
  "rabbia": 1,
  "famiglia": 4,
  "violento": 1,
  "limite": 1,
  "miracolo": 1,
  "scena": 2,
  "spegna": 1,
  "barricato": 1,
  "popolazione": 1,
  "internet": 2,
  "manifestante": 1,
  "morte": 2,
  "volta": 1,
  "cubano": 1,
  "renee": 1,
  "smartphone": 1,
  "modificato": 1,
  "documente": 1,
  "sostituito": 1,
  "macellaio": 1,
  "b&b": 1,
  "privacy": 1,
  "governo": 1,
  "garanto": 1,
  "giornale": 1,
  "mistero": 2,
  "authority": 1,
  "debolezza": 1,
  "segreto": 1,
  "vita": 1,
  "straparlando": 1,
  "fake": 1,
  "giovane": 1,
  "martone": 1,
  "news": 1,
  "argine": 1,
  "decisivo": 1,
  "difesa": 1,
  "zanda": 1,
  "democrazia": 1,
  "sindaco": 2,
  "forza": 1,
  "giudice": 1,
  "restrizione": 1,
  "uso": 1,
  "indagato": 1,
  "giustizia": 1,
  "potere": 1,
  "lezione": 1,
  "mano": 1,
  "arazzo": 1,
  "bayeux": 1,
  "hockney": 1,
  "carta": 1,
  "ladri": 1,
  "pokémon": 1,
  "negozio": 1,
  "escalation": 1,
  "paesi": 1,
  "confronto": 1,
  "dazio": 1,
  "tasso": 2,
  "fmi": 1,
  "inflazione": 1,
  "riparazione": 1,
  "urgente": 1,
  "zaporizhzha": 1,
  "fuoco": 1,
  "sostegno": 1,
  "popolo": 1,
  "iraniano": 1,
  "piazza": 1,
  "sesto": 1,
  "conto": 1,
  "avs": 1,
  "bancomat": 1,
  "m5s": 1,
  "caccia": 1,
  "miliardo": 1,
  "camera": 1,
  "predatorio": 2,
  "mattarella": 2,
  "preoccupazione": 1,
  "ritorno": 1,
  "strategia": 2,
  "peracchini": 1,
  "crescita": 1,
  "impresa": 3,
  "prestito": 1,
  "dicembre": 1,
  "caos": 1,
  "nido": 1,
  "mensa": 1,
  "requisito": 1,
  "iter": 1,
  "domanda": 1,
  "ammontare": 1,
  "collaborazione": 1,
  "antiriciclaggio": 1,
  "pubblico": 2,
  "crolla": 1,
  "stempera": 1,
  "decisione": 1,
  "ambito": 1,
  "giapponese": 1,
  "colosso": 1,
  "divisione": 1,
  "luce": 1,
  "russo": 1,
  "drone": 1,
  "kiev": 1,
  "metà": 1,
  "morto": 2,
  "khamenei": 2,
  "pace": 3,
  "freddo": 1,
  "comitato": 1,
  "lee": 1,
  "incontro": 1,
  "lunedì": 1,
  "79enne": 1,
  "ultimo": 1,
  "guerra": 1,
  "cultura": 2,
  "studente": 1,
  "libero": 1,
  "ispezione": 1,
  "arresto": 1,
  "tassa": 1,
  "cgia": 1,
  "cadavere": 1,
  "fiamma": 1,
  "temporaneo": 1,
  "motore": 1,
  "civiltà": 1,
  "tema": 1,
  "colpevole": 2,
  "membro": 2,
  "politico": 2,
  "rituale": 1,
  "festa": 1,
  "putin": 2,
  "mummia": 1,
  "grotta": 1,
  "ghepardo": 1,
  "consiglio": 1,
  "opportunità": 1,
  "italia-giappone": 2,
  "renzi": 1,
  "tavola": 1,
  "complimento": 1,
  "takaichi": 1,
  "bacchetta": 1,
  "inviato": 1,
  "linea": 1,
  "delegazione": 1,
  "savak": 1,
  "italia-iran": 1,
  "regime": 1,
  "problema": 1,
  "occhio": 1,
  "sole": 1,
  "occhiale": 1,
  "ospedale": 1,
  "incidente": 1,
  "figlio": 1,
  "criminale": 1,
  "zelensky": 1,
  "attacco": 1,
  "colloquio": 1,
  "massiccio": 1,
  "negoziatori": 1,
  "bluff": 1,
  "avanzata": 1,
  "numero": 1,
  "piano": 1,
  "minaccia": 1,
  "peace": 1,
  "usa": 5,
  "tarvisio": 2,
  "spezia": 2,
  "sora": 2,
  "fiorentina": 3,
  "rocco commisso": 2,
  "groenlandia": 11,
  "nato": 6,
  "gaza": 5,
  "iran": 7,
  "minneapolis": 2,
  "strategie predatorie": 2,
  "copenaghen": 2,
  "zaporizhzhia": 2,
  "ucraina": 4,
  "blair": 2,
  "russia": 4
}